io_file_validator/__init__.py
io_file_validator/validator.py
io_file_validator-0.1.5.dist-info/METADATA
io_file_validator-0.1.5.dist-info/WHEEL
io_file_validator-0.1.5.dist-info/RECORD
