Metadata-Version: 2.1
Name: io_file_validator
Version: 0.1.5
Summary: File Validator Tool helps you validate your data with a plethora of formats
Author: Manrique Vargas
Author-email: machomaxg@gmail.com
Requires-Python: >=3.10,<4.0
Classifier: Programming Language :: Python :: 3
Classifier: Programming Language :: Python :: 3.10
Classifier: Programming Language :: Python :: 3.11
Classifier: Programming Language :: Python :: 3.12
Requires-Dist: pandera[io] (>=0.7.2,<0.8.0)
Requires-Dist: pipx (>=1.5.0,<2.0.0)
Requires-Dist: requests (>=2.31.0,<3.0.0)
Requires-Dist: validators (>=0.28.1,<0.29.0)
Requires-Dist: wheel
